tmailor/__init__.py
tmailor/client.py
tmailor/ext/__init__.py
tmailor/ext/utilities/__init__.py
tmailor/ext/utilities/exceptions.py
tmailor/ext/utilities/headers.py
tmailor/ext/utilities/objects.py
tmailor-0.0.12.dist-info/LICENSE
tmailor-0.0.12.dist-info/METADATA
tmailor-0.0.12.dist-info/WHEEL
tmailor-0.0.12.dist-info/top_level.txt
tmailor-0.0.12.dist-info/RECORD
