Metadata-Version: 2.1
Name: tmailor
Version: 0.0.12
Summary: A temporary email address is: a library that provides email addresses without registration, used to receive incoming emails without disclosing your actual email.
Home-page: https://github.com/heromr/tmailor
Author: HeroMR
Author-email: mrhero4006@gmail.com
License: MIT
Keywords: python,tmailor,temp mail,disposable email,temp mailbox,fake email
Classifier: Development Status :: 5 - Production/Stable
Classifier: Intended Audience :: Developers
Classifier: Programming Language :: Python :: 3
Classifier: Operating System :: OS Independent
License-File: LICENSE
